databricks_genai_inference/__init__.py
databricks_genai_inference/version.py
databricks_genai_inference/api/__init__.py
databricks_genai_inference/api/chat_completion.py
databricks_genai_inference/api/chat_session.py
databricks_genai_inference/api/completion.py
databricks_genai_inference/api/embedding.py
databricks_genai_inference/api/exception.py
databricks_genai_inference/api/util.py
databricks_genai_inference/api/abstract/__init__.py
databricks_genai_inference/api/abstract/api_resource.py
databricks_genai_inference/api/abstract/foundation_model_api_resource.py
databricks_genai_inference/api/abstract/foundation_model_object.py
databricks_genai_inference/api/objects/__init__.py
databricks_genai_inference/api/objects/chat_completion_chunk_object.py
databricks_genai_inference/api/objects/chat_completion_object.py
databricks_genai_inference/api/objects/completion_chunk_object.py
databricks_genai_inference/api/objects/completion_object.py
databricks_genai_inference/api/objects/embedding_object.py
wfork_databricks_genai_inference-2.0.2.dist-info/METADATA
wfork_databricks_genai_inference-2.0.2.dist-info/WHEEL
wfork_databricks_genai_inference-2.0.2.dist-info/top_level.txt
wfork_databricks_genai_inference-2.0.2.dist-info/RECORD
